zoocut/HMM-train.py
zoocut/LM-train.py
zoocut/__init__.py
zoocut/cut.py
zoocut/evaluate.py
zoocut/__pycache__/__init__.cpython-35.pyc
zoocut/__pycache__/cut.cpython-35.pyc
zoocut/data/dict_chinese_corpus.txt
zoocut/data/dict_weibo.txt
zoocut/hmm/prob_emit_chinese_corpus.pkl
zoocut/hmm/prob_emit_weibo.pkl
zoocut/hmm/prob_start_chinese_corpus.pkl
zoocut/hmm/prob_start_weibo.pkl
zoocut/hmm/prob_trans_chinese_corpus.pkl
zoocut/hmm/prob_trans_weibo.pkl
zoocut/lm/model_chinese_corpus.pkl
zoocut/lm/model_weibo.pkl
zoocut-0.1.dist-info/METADATA
zoocut-0.1.dist-info/RECORD
zoocut-0.1.dist-info/WHEEL
zoocut-0.1.dist-info/top_level.txt
