Metadata-Version: 2.1
Name: zoocut
Version: 0.1
Summary: A Chinese word segmentation tool
Home-page: http://github.com/tongling/clinicaltrial
Author: BearAndGirl
Author-email: yuanhaoda17@mails.ucas.ac.cn
License: MIT
Platform: UNKNOWN
